{
	"name": "m066",
	"isomorphism signature": "fLLQccceddehwxwwj",
	"N": 5,
	"a": [
		0.06036317841348201,
		0.05720474201160757,
		0.8824320795749104,
		0.42580740656816285,
		0.23513584085017916,
		0.33905675258165796,
		0.25189941511849134,
		0.6323408764125383,
		0.11575970846897042,
		0.25189941511849134,
		0.6323408764125383,
		0.11575970846897042,
		0.46665525778811995,
		0.16568561862441825,
		0.3676591235874618
	],
	"L": [
		[
			-1,
			2,
			-1,
			0,
			2,
			-2,
			0,
			1,
			-1,
			0,
			1,
			-1,
			0,
			1,
			-1
		],
		[
			-1,
			0,
			1,
			2,
			-2,
			0,
			-1,
			0,
			1,
			-1,
			0,
			1,
			0,
			0,
			0
		],
		[
			2,
			-2,
			0,
			-1,
			0,
			1,
			0,
			0,
			0,
			0,
			0,
			0,
			0,
			0,
			0
		],
		[
			0,
			0,
			0,
			-1,
			0,
			1,
			2,
			-1,
			-1,
			2,
			-1,
			-1,
			-2,
			1,
			1
		],
		[
			0,
			0,
			0,
			0,
			0,
			0,
			-1,
			0,
			1,
			-1,
			0,
			1,
			2,
			-2,
			0
		],
		[
			0,
			0,
			0,
			0,
			0,
			0,
			-1,
			1,
			0,
			1,
			-1,
			0,
			0,
			0,
			0
		],
		[
			0,
			0,
			0,
			0,
			0,
			0,
			-1,
			2,
			-1,
			1,
			-2,
			1,
			0,
			0,
			0
		]
	]
}