{
	"name": "m257",
	"isomorphism signature": "fLAMcaccdeejnbxhj",
	"N": 5,
	"a": [
		0.27971658750763895,
		0.40445831358454853,
		0.3158250989078125,
		0.35193361030798603,
		0.19081282449098252,
		0.45725356520103144,
		0.40445831358454853,
		0.3158250989078125,
		0.27971658750763895,
		0.40445831358454853,
		0.3158250989078125,
		0.27971658750763895,
		0.824033194846007,
		0.10060943727484696,
		0.07535736787914604
	],
	"L": [
		[
			-1,
			1,
			0,
			0,
			1,
			-1,
			1,
			0,
			-1,
			1,
			-1,
			0,
			0,
			0,
			0
		],
		[
			-1,
			0,
			1,
			2,
			-2,
			0,
			0,
			1,
			-1,
			0,
			0,
			0,
			-1,
			-1,
			2
		],
		[
			1,
			-1,
			0,
			-2,
			0,
			2,
			-1,
			0,
			1,
			-1,
			-1,
			2,
			1,
			-1,
			0
		],
		[
			1,
			0,
			-1,
			0,
			0,
			0,
			0,
			-1,
			1,
			0,
			2,
			-2,
			0,
			0,
			0
		],
		[
			0,
			0,
			0,
			0,
			1,
			-1,
			0,
			0,
			0,
			0,
			0,
			0,
			0,
			2,
			-2
		],
		[
			0,
			-1,
			1,
			0,
			0,
			0,
			1,
			-1,
			0,
			0,
			0,
			0,
			0,
			0,
			0
		],
		[
			-1,
			1,
			0,
			-2,
			2,
			0,
			-1,
			0,
			1,
			0,
			-2,
			2,
			1,
			1,
			-2
		]
	]
}