{
	"name": "m282",
	"isomorphism signature": "fLAMcaccdeejnjxxn",
	"N": 5,
	"a": [
		0.2871563021306138,
		0.3226084719033626,
		0.39023522596602367,
		0.39023522596602367,
		0.2871563021306138,
		0.3226084719033626,
		0.18634129825650342,
		0.6097647740339764,
		0.20389392770952022,
		0.2869149850070359,
		0.45887564555022176,
		0.2542093694427424,
		0.2066404819179755,
		0.12611758181612312,
		0.6672419362659014
	],
	"L": [
		[
			1,
			0,
			-1,
			-1,
			1,
			0,
			0,
			1,
			-1,
			-1,
			0,
			1,
			0,
			0,
			0
		],
		[
			-1,
			1,
			0,
			0,
			-1,
			1,
			0,
			0,
			0,
			0,
			2,
			-2,
			0,
			1,
			-1
		],
		[
			1,
			-1,
			0,
			0,
			1,
			-1,
			-2,
			0,
			2,
			0,
			0,
			0,
			0,
			0,
			0
		],
		[
			-1,
			0,
			1,
			1,
			-1,
			0,
			2,
			-1,
			-1,
			2,
			-2,
			0,
			-2,
			0,
			2
		],
		[
			0,
			0,
			0,
			0,
			0,
			0,
			0,
			0,
			0,
			-1,
			0,
			1,
			2,
			-1,
			-1
		],
		[
			1,
			-2,
			1,
			-1,
			1,
			0,
			0,
			0,
			0,
			1,
			-2,
			1,
			-2,
			0,
			2
		],
		[
			-1,
			0,
			1,
			-1,
			1,
			0,
			2,
			0,
			-2,
			1,
			-2,
			1,
			-2,
			0,
			2
		]
	]
}