{
	"name": "m397",
	"isomorphism signature": "fLLQcacdedejkqasj",
	"N": 5,
	"a": [
		0.4355443905356848,
		0.30546857883589573,
		0.25898703062841955,
		0.4117213200463674,
		0.3004181846409416,
		0.287860495312691,
		0.4117213200463674,
		0.3004181846409416,
		0.287860495312691,
		0.3330754610489184,
		0.392867484744902,
		0.27405705420617965,
		0.28407668358898563,
		0.2753285316803755,
		0.44059478473063884
	],
	"L": [
		[
			-1,
			2,
			-1,
			0,
			1,
			-1,
			0,
			1,
			-1,
			0,
			0,
			0,
			0,
			0,
			0
		],
		[
			-1,
			0,
			1,
			1,
			-1,
			0,
			1,
			-1,
			0,
			-2,
			1,
			1,
			0,
			0,
			0
		],
		[
			2,
			-2,
			0,
			-1,
			0,
			1,
			-1,
			0,
			1,
			0,
			0,
			0,
			2,
			-2,
			0
		],
		[
			0,
			0,
			0,
			0,
			-1,
			1,
			0,
			-1,
			1,
			2,
			-2,
			0,
			-1,
			0,
			1
		],
		[
			0,
			0,
			0,
			0,
			1,
			-1,
			0,
			1,
			-1,
			0,
			1,
			-1,
			-1,
			2,
			-1
		],
		[
			-1,
			0,
			1,
			0,
			0,
			0,
			2,
			-2,
			0,
			-2,
			1,
			1,
			0,
			0,
			0
		],
		[
			1,
			0,
			-1,
			0,
			1,
			-1,
			-2,
			1,
			1,
			2,
			-1,
			-1,
			0,
			0,
			0
		]
	]
}